rfscrapper/__init__.py
rfscrapper/main.py
rfscrapper/rf_scrapper.py
rfscrapper-2.dist-info/LICENSE
rfscrapper-2.dist-info/METADATA
rfscrapper-2.dist-info/WHEEL
rfscrapper-2.dist-info/entry_points.txt
rfscrapper-2.dist-info/top_level.txt
rfscrapper-2.dist-info/RECORD
