Metadata-Version: 2.1
Name: rfscrapper
Version: 2
Summary: A simple web scrapper tool wich downloads podcasts from radiofrance.
Home-page: https://github.com/Cosmow22/radio-france-podcasts-scrapper
Author: Cosmow22
Author-email: cosmow543@gmail.com
License: MIT
Classifier: License :: OSI Approved :: MIT License
Classifier: Programming Language :: Python :: 3
Classifier: Operating System :: OS Independent
Requires-Python: >=3.6
License-File: LICENSE
